{
  "todos": [
    {
      "id": "7b434abd-e061-417a-9d60-077bf2282eb5",
      "title": "hoc node",
      "completed": false,
      "createdAt": "2026-07-06T10:40:32.543Z"
    },
    {
      "id": "503961f4-be03-45fc-ad73-2893cfd3ef45",
      "title": "",
      "completed": false,
      "createdAt": "2026-07-06T11:01:42.608Z"
    },
    {
      "id": "1a375a48-7d11-4637-bcbb-eea228158850",
      "title": "asd",
      "completed": false,
      "createdAt": "2026-07-06T11:01:46.363Z"
    },
    {
      "id": "60aadc57-ec82-43fb-9824-346016705808",
      "title": "aqeqwesd",
      "completed": false,
      "createdAt": "2026-07-06T11:01:50.257Z"
    },
    {
      "id": "444090e7-d0b5-4c69-a26b-85ed68757cbd",
      "title": "Todo A",
      "completed": false,
      "createdAt": "2026-07-06T11:04:42.429Z"
    },
    {
      "id": "0dc9f94c-30a5-496c-af57-0449ed86efce",
      "title": "Todo B",
      "completed": false,
      "createdAt": "2026-07-06T11:05:11.193Z"
    },
    {
      "id": "515cae88-de5c-45e5-84ce-801f32af0013",
      "title": "Todo C",
      "completed": false,
      "createdAt": "2026-07-06T11:05:19.801Z"
    }
  ]
}